{"dependencies":[{"name":"_css_loader"}],"generated":{"css":"body {\r\n    position: relative;\r\n    width: 100%;\r\n    height: 100%;\r\n    background-color: #edf7ff;\r\n}\r\n   \r\nhtml {\r\n    width: 100%;\r\n    height: 100%;\r\n}\r\n   \r\nh1 {\r\n    font-family: 'Roboto', sans-serif;\r\n    font-weight: 700;\r\n    margin: 0 0 35px;\r\n    letter-spacing: 1px;\r\n    text-transform: uppercase;\r\n    font-size: 100px;\r\n    color: black;\r\n}\r\n\r\n.sub-font {\r\n    font-size: 50px;\r\n}\r\n\r\n.in-block {\r\n    display: inline-block;\r\n}\r\n\r\n.main-header {\r\n    display: table;\r\n    width: 100%;\r\n    height: auto;\r\n    padding: 200px 0;\r\n    text-align: center;\r\n}\r\n   \r\n.intro-body {\r\n    display: table-cell;\r\n    vertical-align: middle;\r\n}\r\n\r\n.nav {\r\n    font-size: 22px;\r\n    font-weight: 400;\r\n    font-family: 'Roboto';\r\n}","js":"\n        var reloadCSS = require('_css_loader');\n        module.hot.dispose(reloadCSS);\n        module.hot.accept(reloadCSS);\n      "},"hash":"f0e65e748ac94f11a51be7d2c1ad20f8","cacheData":{}}